{
  "model_path": "/Users/cayofel/Documents/GitHub/isomera_v2/main/data/architectures/tpc_ds_genai_spec_protocol/screening_models/focal_loss_lr0p001_h32_d0p1_t0p4/graph_SOR16_D5_seed42.pkl",
  "scenarios": [
    "graph_SOR16_D5_seed42"
  ],
  "dataset_summary": [
    {
      "scenario": "graph_SOR16_D5_seed42",
      "positive_pairs": 93,
      "negative_pairs": 342,
      "dataset_rows": 435,
      "skipped_rows": 0,
      "dataset_source": "supervised_validation_dataset"
    }
  ],
  "epochs": 5,
  "learning_rate": 0.001,
  "hidden_channels": 32,
  "dropout": 0.1,
  "negative_ratio": 1,
  "train_ratio": 0.8,
  "test_ratio": 0.2,
  "balance_strategy": "none_real_distribution",
  "balance_strategy_label": "Use real distribution without balancing (no sampler/no class weight)",
  "balance_summary": {
    "strategy": "none_real_distribution",
    "before": {
      "positive_pairs": 74,
      "negative_pairs": 273,
      "dataset_rows": 347
    },
    "after": {
      "positive_pairs": 74,
      "negative_pairs": 273,
      "dataset_rows": 347
    },
    "operation": "kept_original_training_rows"
  },
  "seed": 42,
  "optimizer": "adam",
  "optimizer_label": "Adaptive gradient optimizer (torch.optim.Adam)",
  "optimizer_name": "torch.optim.Adam",
  "configured_loss": "focal_loss",
  "configured_loss_label": "Focal loss for rare duplicates (custom sigmoid focal loss)",
  "loss": {
    "loss_key": "focal_loss",
    "loss_name": "custom sigmoid focal loss",
    "loss_label": "Focal loss for rare duplicates (custom sigmoid focal loss)",
    "formula": "FL(p_t) = -alpha * (1 - p_t)^gamma * log(p_t)",
    "alpha": 0.25,
    "gamma": 2.0,
    "pos_weight": null
  },
  "loss_name": "custom sigmoid focal loss",
  "train_distribution": {
    "positive_pairs": 74,
    "negative_pairs": 273,
    "dataset_rows": 347
  },
  "val_distribution": {
    "positive_pairs": 19,
    "negative_pairs": 69,
    "dataset_rows": 88
  },
  "history": [
    {
      "epoch": 1,
      "train_loss": 0.057415,
      "train_accuracy": 0.778098,
      "val_loss": 0.057429,
      "val_accuracy": 0.784091,
      "epoch_seconds": 0.466094
    },
    {
      "epoch": 2,
      "train_loss": 0.053561,
      "train_accuracy": 0.786744,
      "val_loss": 0.056746,
      "val_accuracy": 0.784091,
      "epoch_seconds": 0.401466
    },
    {
      "epoch": 3,
      "train_loss": 0.052693,
      "train_accuracy": 0.786744,
      "val_loss": 0.050695,
      "val_accuracy": 0.784091,
      "epoch_seconds": 0.402045
    },
    {
      "epoch": 4,
      "train_loss": 0.0524,
      "train_accuracy": 0.786744,
      "val_loss": 0.054104,
      "val_accuracy": 0.784091,
      "epoch_seconds": 0.428203
    },
    {
      "epoch": 5,
      "train_loss": 0.052335,
      "train_accuracy": 0.786744,
      "val_loss": 0.050602,
      "val_accuracy": 0.784091,
      "epoch_seconds": 0.402174
    }
  ],
  "train_size": 347,
  "val_size": 88,
  "status": "completed",
  "config_id": "focal_loss_lr0p001_h32_d0p1_t0p4",
  "protocol_stage": "screening",
  "inference_threshold": 0.4,
  "wall_seconds": 2.151743,
  "model_family": "GNN GenAI Spec Protocol Focal Loss"
}